submission.py
submission-0.0.3.dist-info/METADATA
submission-0.0.3.dist-info/WHEEL
submission-0.0.3.dist-info/top_level.txt
submission-0.0.3.dist-info/RECORD
