Metadata-Version: 2.1
Name: submission
Version: 0.0.3
Summary: Takes algorithm, train, test, X variables, Y variables, column names required for submission and name of submission file as input and produces an output csv for submitting in the competition.
Home-page: UNKNOWN
Author: UNKNOWN
Author-email: UNKNOWN
License: UNKNOWN
Platform: UNKNOWN
